split_normal/__init__.py
split_normal/_base.py
split_normal/jax.py
split_normal/numpy.py
split_normal/version.py
split_normal-0.1.0a0.dist-info/LICENSE
split_normal-0.1.0a0.dist-info/METADATA
split_normal-0.1.0a0.dist-info/WHEEL
split_normal-0.1.0a0.dist-info/top_level.txt
split_normal-0.1.0a0.dist-info/RECORD
