Metadata-Version: 2.1
Name: split-normal
Version: 0.1.0a0
Summary: A tiny package implementing functions of the split normal distribution compatible with Numpy and JAX.
Home-page: https://github.com/probablyai/split-normal
Author: Tárik S. Salem
License: UNKNOWN
Platform: UNKNOWN
Classifier: Programming Language :: Python :: 3
Classifier: License :: OSI Approved :: MIT License
Classifier: Operating System :: OS Independent
Classifier: Topic :: Scientific/Engineering
Classifier: Topic :: Software Development
Requires-Python: >=3.6
Requires-Dist: numpy (>=1.17.3)
Requires-Dist: scipy (>=1.4.0)
Requires-Dist: jax (>=0.1.59)
Requires-Dist: jaxlib (>=0.1.40)
Provides-Extra: dev
Requires-Dist: pytest (>=5.4.2) ; extra == 'dev'
Requires-Dist: readme2tex (>=0.0.1b2) ; extra == 'dev'
Requires-Dist: GitPython (>=3.1.3) ; extra == 'dev'
